{"config": {"view": {"continuousWidth": 300, "continuousHeight": 300}}, "data": {"url": "https://raw.githubusercontent.com/zihzi/DATA2Poster/refs/heads/main/data/Cars.csv"}, "mark": "boxplot", "encoding": {"color": {"field": "Cylinders", "legend": {"title": "Cylinders"}, "type": "ordinal"}, "x": {"axis": {"title": "Year"}, "field": "Year", "sort": "ascending", "timeUnit": "year", "type": "temporal"}, "y": {"axis": {"title": "Displacement"}, "field": "Displacement", "type": "quantitative"}}, "$schema": "https://vega.github.io/schema/vega-lite/v5.json"}